<?xml version="1.0" encoding="UTF-8"?>
<fmiModelDescription
  fmiVersion="2.0"
  modelName="SpaceStation"
  guid="{8c4e810f-3df3-4a00-8276-176fa3c9f9e0}"
  description=""
  generationTool="OpenModelica Compiler OMCompiler v1.13.0-dev.166+ga33d4f3"
  generationDateAndTime="2017-11-26T21:32:21Z"
  variableNamingConvention="structured"
  numberOfEventIndicators="0">
  <CoSimulation
    modelIdentifier="space_station_fmu"
    needsExecutionTool="false"
    canHandleVariableCommunicationStepSize="true"
    canInterpolateInputs="false"
    maxOutputDerivativeOrder="1"
    canRunAsynchronuously = "false"
    canBeInstantiatedOnlyOncePerProcess="false"
    canNotUseMemoryManagementFunctions="false"
    canGetAndSetFMUstate="false"
    canSerializeFMUstate="false"
     />
  <LogCategories>
    <Category name="logEvents" />
    <Category name="logSingularLinearSystems" />
    <Category name="logNonlinearSystems" />
    <Category name="logDynamicStateSelection" />
    <Category name="logStatusWarning" />
    <Category name="logStatusDiscard" />
    <Category name="logStatusError" />
    <Category name="logStatusFatal" />
    <Category name="logStatusPending" />
    <Category name="logAll" />
    <Category name="logFmi2Call" />
  </LogCategories>
  <DefaultExperiment startTime="0.0" stopTime="1.0" tolerance="1e-06"/>
  <ModelVariables>
  <!-- Index of variable = "1" -->
  <ScalarVariable
    name="stationx"
    valueReference="0"
    variability="continuous"
    causality="local"
    initial="calculated">
    <Real/>
  </ScalarVariable>
  <!-- Index of variable = "2" -->
  <ScalarVariable
    name="stationy"
    valueReference="1"
    variability="continuous"
    causality="local"
    initial="calculated">
    <Real derivative="1"/>
  </ScalarVariable>
  <!-- Index of variable = "3" -->
  <ScalarVariable
    name="earthx"
    valueReference="2"
    variability="continuous"
    causality="local"
    initial="calculated">
    <Real/>
  </ScalarVariable>
  <!-- Index of variable = "4" -->
  <ScalarVariable
    name="earthy"
    valueReference="3"
    variability="continuous"
    causality="local"
    initial="calculated">
    <Real/>
  </ScalarVariable>
  </ModelVariables>
  <ModelStructure>
    <Derivatives>
      <Unknown index="2" dependencies="1" dependenciesKind="dependent" />
    </Derivatives>
  </ModelStructure>
</fmiModelDescription>